hnu_quant_db/__init__.py
hnu_quant_db/core.py
hnu_quant_db/psql_query.py
hnu_quant_db/sourcedata.py
hnu_quant_db-0.0.29.dist-info/METADATA
hnu_quant_db-0.0.29.dist-info/WHEEL
hnu_quant_db-0.0.29.dist-info/top_level.txt
hnu_quant_db-0.0.29.dist-info/RECORD
